{
    "key": "group_5cbf07ca23b40",
    "title": "Gallery",
    "fields": [
        {
            "key": "field_525d529f9d4e2",
            "label": "Subtitle",
            "name": "subtitle",
            "type": "text",
            "instructions": "",
            "required": 0,
            "conditional_logic": 0,
            "wrapper": {
                "width": "",
                "class": "",
                "id": ""
            },
            "default_value": "",
            "placeholder": "",
            "prepend": "",
            "append": "",
            "formatting": "html",
            "maxlength": ""
        },
        {
            "key": "field_525d5574f5c66",
            "label": "Read more",
            "name": "read_more",
            "type": "page_link",
            "instructions": "",
            "required": 0,
            "conditional_logic": 0,
            "wrapper": {
                "width": "",
                "class": "",
                "id": ""
            },
            "post_type": [
                "post",
                "page",
                "subsidiary"
            ],
            "allow_null": 1,
            "multiple": 0,
            "taxonomy": [],
            "allow_archives": 1
        }
    ],
    "location": [
        [
            {
                "param": "post_type",
                "operator": "==",
                "value": "gallery"
            }
        ]
    ],
    "menu_order": 0,
    "position": "normal",
    "style": "default",
    "label_placement": "top",
    "instruction_placement": "label",
    "hide_on_screen": [
        "excerpt"
    ],
    "active": 1,
    "description": "",
    "modified": 1571242147
}